mysql_mcp_server_pro_plus/__init__.py
mysql_mcp_server_pro_plus/config.py
mysql_mcp_server_pro_plus/db_manager.py
mysql_mcp_server_pro_plus/logger.py
mysql_mcp_server_pro_plus/schema_mapping.py
mysql_mcp_server_pro_plus/server.py
mysql_mcp_server_pro_plus/validator.py
mysql_mcp_server_pro_plus/tools/__init__.py
mysql_mcp_server_pro_plus/tools/analyze_db_health.py
mysql_mcp_server_pro_plus/tools/analyze_query_performance.py
mysql_mcp_server_pro_plus/tools/describe_table.py
mysql_mcp_server_pro_plus/tools/discover_sensitive_data.py
mysql_mcp_server_pro_plus/tools/execute_sql.py
mysql_mcp_server_pro_plus/tools/explore_interactive.py
mysql_mcp_server_pro_plus/tools/get_blocking_queries.py
mysql_mcp_server_pro_plus/tools/get_database_overview.py
mysql_mcp_server_pro_plus/tools/get_schema_visualization.py
mysql_mcp_server_pro_plus/tools/list_tables.py
mysql_mcp_server_pro_plus-0.3.2.dist-info/licenses/LICENSE
mysql_mcp_server_pro_plus-0.3.2.dist-info/METADATA
mysql_mcp_server_pro_plus-0.3.2.dist-info/WHEEL
mysql_mcp_server_pro_plus-0.3.2.dist-info/entry_points.txt
mysql_mcp_server_pro_plus-0.3.2.dist-info/top_level.txt
mysql_mcp_server_pro_plus-0.3.2.dist-info/RECORD
