Metadata-Version: 2.4
Name: mysql_mcp_server_pro_plus
Version: 0.3.2
Summary: A Model Context Protocol (MCP) server that enables secure interaction with MySQL databases. This server allows AI assistants to list tables, read data, and execute SQL queries through a controlled interface, making database exploration and analysis safer and more structured.
Author-email: "Dana K. Williams" <dana_w@designcomputer.com>, Henry Bui <minhduc2k31905@gmail.com>
License-Expression: MIT
Requires-Python: >=3.11
License-File: LICENSE
Requires-Dist: fastmcp==2.14.1
Requires-Dist: loguru>=0.7.3
Requires-Dist: mysql-connector-python==8.2.0
Requires-Dist: pre-commit>=4.2.0
Requires-Dist: psutil>=7.0.0
Requires-Dist: pyrefly>=0.27.0
Dynamic: license-file
